easypyplot/__init__.py
easypyplot/barchart.py
easypyplot/color.py
easypyplot/format.py
easypyplot/math.py
easypyplot/pdf.py
easypyplot/util.py
easypyplot/tests/__init__.py
easypyplot/tests/test_barchart.py
easypyplot/tests/test_color.py
easypyplot/tests/test_format.py
easypyplot/tests/test_math.py
easypyplot/tests/test_pdf.py
easypyplot/tests/test_util.py
easypyplot/tests/baseline_images/test_barchart/barchart_base.pdf
easypyplot/tests/baseline_images/test_barchart/barchart_base.png
easypyplot/tests/baseline_images/test_barchart/barchart_base.svg
easypyplot/tests/baseline_images/test_barchart/barchart_cbshrk.pdf
easypyplot/tests/baseline_images/test_barchart/barchart_cbshrk.png
easypyplot/tests/baseline_images/test_barchart/barchart_cbshrk.svg
easypyplot/tests/baseline_images/test_barchart/barchart_cbshrk_nobkdn.pdf
easypyplot/tests/baseline_images/test_barchart/barchart_cbshrk_nobkdn.png
easypyplot/tests/baseline_images/test_barchart/barchart_cbshrk_nobkdn.svg
easypyplot/tests/baseline_images/test_barchart/barchart_colors.pdf
easypyplot/tests/baseline_images/test_barchart/barchart_colors.png
easypyplot/tests/baseline_images/test_barchart/barchart_colors.svg
easypyplot/tests/baseline_images/test_barchart/barchart_colors_nobkdn.pdf
easypyplot/tests/baseline_images/test_barchart/barchart_colors_nobkdn.png
easypyplot/tests/baseline_images/test_barchart/barchart_colors_nobkdn.svg
easypyplot/tests/baseline_images/test_barchart/barchart_edgecolor.pdf
easypyplot/tests/baseline_images/test_barchart/barchart_edgecolor.png
easypyplot/tests/baseline_images/test_barchart/barchart_edgecolor.svg
easypyplot/tests/baseline_images/test_barchart/barchart_edgecolor_none.pdf
easypyplot/tests/baseline_images/test_barchart/barchart_edgecolor_none.png
easypyplot/tests/baseline_images/test_barchart/barchart_edgecolor_none.svg
easypyplot/tests/baseline_images/test_barchart/barchart_entry_names.pdf
easypyplot/tests/baseline_images/test_barchart/barchart_entry_names.png
easypyplot-1.2.0.dist-info/LICENSE
easypyplot-1.2.0.dist-info/METADATA
easypyplot-1.2.0.dist-info/WHEEL
easypyplot-1.2.0.dist-info/top_level.txt
easypyplot-1.2.0.dist-info/RECORD
