Metadata-Version: 2.1
Name: easypyplot
Version: 1.2.0
Summary: Lightweight utilities and wrappers for Python matplotlib.
Home-page: https://github.com/gaomy3832/easypyplot
Author: Mingyu Gao
Author-email: gaomy@tsinghua.edu.cn
License: BSD 3-clause
Keywords: matplotlib python-plot
Platform: UNKNOWN
Classifier: Development Status :: 3 - Alpha
Classifier: Intended Audience :: Developers
Classifier: Intended Audience :: Science/Research
Classifier: License :: OSI Approved :: BSD License
Classifier: Programming Language :: Python :: 2.7
Classifier: Programming Language :: Python :: 3.4
Classifier: Programming Language :: Python :: 3.5
Classifier: Programming Language :: Python :: 3.6
Classifier: Programming Language :: Python :: 3.7
Classifier: Programming Language :: Python :: 3.8
Classifier: Topic :: Artistic Software
Classifier: Topic :: Multimedia :: Graphics :: Presentation
Classifier: Topic :: Scientific/Engineering :: Visualization
Classifier: Topic :: Utilities
Requires-Dist: coverage (>=4)
Requires-Dist: matplotlib (>=1.3)
Requires-Dist: cycler (>=0.10)
Requires-Dist: nose (>=1.3)
Requires-Dist: pytest (>=3)
Requires-Dist: pytest-cov (>=2)
Requires-Dist: pytest-xdist (>=1)
